{
  "parent": "jellyfishing:jellyfishing/catch",
  "display": {
    "icon": {
      "item": "jellyfishing:jellyfish_jelly"
    },
    "title": {
      "translate": "advancements.jellyfishing.jelly.title"
    },
    "description": {
      "translate": "advancements.jellyfishing.jelly.description"
    },
    "frame": "task",
    "show_toast": true,
    "announce_to_chat": true,
    "hidden": false
  },
  "criteria": {
    "net": {
      "trigger": "minecraft:inventory_changed",
      "conditions": {
        "items": [
          {
            "tag": "jellyfishing:jelly"
          },
          {
            "item": "jellyfishing:jellyfish_net"
          }
        ]
      }
    }
  },
  "requirements": [
    [
      "net"
    ]
  ]
}